zww_test_package/__init__.py
zww_test_package/core.py
zww_test_package/test_core.py
zww_test_package/libs/libsixvan.so
zww_test_package2/__init__.py
zww_test_package2/core.py
zww_test_package2/test_core.py
zww_test_package-1.0.3.dist-info/LICENSE
zww_test_package-1.0.3.dist-info/METADATA
zww_test_package-1.0.3.dist-info/WHEEL
zww_test_package-1.0.3.dist-info/top_level.txt
zww_test_package-1.0.3.dist-info/RECORD
