Metadata-Version: 2.1
Name: zww-test-package
Version: 1.0.3
Summary: 测试代码调用
Author: Peter Zhao
Author-email: zhaowenweu@shinetechsoftware.com
Classifier: Programming Language :: Python :: 3
Classifier: License :: OSI Approved :: MIT License
Classifier: Operating System :: OS Independent
Requires-Python: >=3
License-File: LICENSE
